DisFormers/__init__.py
DisFormers/disformers.py
disformers-0.10.7.dist-info/LICENSE
disformers-0.10.7.dist-info/METADATA
disformers-0.10.7.dist-info/WHEEL
disformers-0.10.7.dist-info/top_level.txt
disformers-0.10.7.dist-info/RECORD
